_rizin.cpython-38-x86_64-linux-gnu.so
rz_bindings-0.6.0.dist-info/RECORD
rz_bindings-0.6.0.dist-info/METADATA
rz_bindings-0.6.0.dist-info/WHEEL
rz_bindings-0.6.0.data/purelib/rizin.py
rz_bindings.libs/libgcc_s-a04fdf82.so.1
rz_bindings.libs/librz_crypto-417992c1.so.0.6.0
rz_bindings.libs/librz_demangler-14368801.so.0.6.0
rz_bindings.libs/librz_sign-31a7f392.so.0.6.0
rz_bindings.libs/librz_reg-6bad8c28.so.0.6.0
rz_bindings.libs/librz_hash-e1db3cc1.so.0.6.0
rz_bindings.libs/librz_asm-89ae93c7.so.0.6.0
rz_bindings.libs/librz_flag-cf275c5e.so.0.6.0
rz_bindings.libs/librz_io-90dbfeb7.so.0.6.0
rz_bindings.libs/librz_syscall-de675cbb.so.0.6.0
rz_bindings.libs/librz_type-2e159721.so.0.6.0
rz_bindings.libs/librz_parse-f356e1c1.so.0.6.0
rz_bindings.libs/librz_lang-aca914f0.so.0.6.0
rz_bindings.libs/librz_util-535ecddc.so.0.6.0
rz_bindings.libs/librz_core-d11b61e7.so.0.6.0
rz_bindings.libs/librz_bp-7f438ed7.so.0.6.0
rz_bindings.libs/librz_analysis-e4a0420b.so.0.6.0
rz_bindings.libs/librz_bin-0dc65cec.so.0.6.0
rz_bindings.libs/librz_socket-8c77922a.so.0.6.0
rz_bindings.libs/libstdc++-a9383cce.so.6.0.28
rz_bindings.libs/librz_debug-df6c1ed4.so.0.6.0
rz_bindings.libs/librz_cons-a57f4da9.so.0.6.0
rz_bindings.libs/librz_config-ba48503b.so.0.6.0
rz_bindings.libs/librz_diff-9ffcca4b.so.0.6.0
rz_bindings.libs/librz_search-6507f0b7.so.0.6.0
rz_bindings.libs/librz_il-1c31dcca.so.0.6.0
rz_bindings.libs/librz_magic-2eb6ba93.so.0.6.0
rz_bindings.libs/librz_egg-85ed3974.so.0.6.0
