Metadata-Version: 2.1
Name: rz-bindings
Version: 0.6.0
Requires-Python: >=3.8
